Changelog
LICENSE
MANIFEST.in
setup.py
test.py
Zvbi.egg-info/PKG-INFO
Zvbi.egg-info/SOURCES.txt
Zvbi.egg-info/dependency_links.txt
Zvbi.egg-info/top_level.txt
doc/README.rst
doc/ZVBI.rst
examples/browse-ttx.py
examples/caption.py
examples/capture.py
examples/decode.py
examples/dvb-demux.py
examples/dvb-mux.py
examples/explist.py
examples/export.py
examples/hamm.py
examples/network.py
examples/osc.py
examples/proxy-test.py
examples/search-ttx.py
examples/test-vps.py
src/libzvbi_int.h
src/zvbi.c
src/zvbi_callbacks.c
src/zvbi_callbacks.h
src/zvbi_capture.c
src/zvbi_capture.h
src/zvbi_capture_buf.c
src/zvbi_capture_buf.h
src/zvbi_dvb_demux.c
src/zvbi_dvb_demux.h
src/zvbi_dvb_mux.c
src/zvbi_dvb_mux.h
src/zvbi_event_types.c
src/zvbi_event_types.h
src/zvbi_export.c
src/zvbi_export.h
src/zvbi_idl_demux.c
src/zvbi_idl_demux.h
src/zvbi_page.c
src/zvbi_page.h
src/zvbi_pfc_demux.c
src/zvbi_pfc_demux.h
src/zvbi_proxy.c
src/zvbi_proxy.h
src/zvbi_raw_dec.c
src/zvbi_raw_dec.h
src/zvbi_raw_params.c
src/zvbi_raw_params.h
src/zvbi_search.c
src/zvbi_search.h
src/zvbi_service_dec.c
src/zvbi_service_dec.h
src/zvbi_xds_demux.c
src/zvbi_xds_demux.h