Metadata-Version: 2.1
Name: Zvbi
Version: 0.1.1
Summary: Interface to the Zapping VBI decoder library
Home-page: https://github.com/tomzox/Python-ZVBI
Author: T. Zoerner
Author-email: tomzo@users.sourceforge.net
License: GNU GPLv2
Keywords: teletext,videotext,closed-caption,VPS,WSS,VBI,DVB,video,capture,decoder,libzvbi,ETSI
Platform: posix
Classifier: Development Status :: 4 - Beta
Classifier: Programming Language :: C
Classifier: Programming Language :: Python :: 3
Classifier: Topic :: Multimedia :: Video :: Capture
Classifier: Intended Audience :: Developers
Classifier: Operating System :: POSIX :: Linux
Classifier: Operating System :: POSIX :: BSD
Classifier: License :: OSI Approved :: GNU General Public License v2 (GPLv2)
Requires-Python: >=3.2
